pytest_ssh/__init__.py
pytest_ssh/plugin.py
pytest_ssh/ssh.py
pytest_ssh-0.1.dist-info/METADATA
pytest_ssh-0.1.dist-info/WHEEL
pytest_ssh-0.1.dist-info/entry_points.txt
pytest_ssh-0.1.dist-info/top_level.txt
pytest_ssh-0.1.dist-info/RECORD
