Metadata-Version: 2.1
Name: pytest-ssh
Version: 0.1
Summary: pytest plugin for ssh command run
Home-page: https://github.com/liangxiao1/pytest-ssh
Author: Xiao Liang
Author-email: xiliang@redhat.com
License: MIT
Platform: UNKNOWN
Classifier: Framework :: Pytest
Classifier: Programming Language :: Python
Classifier: Programming Language :: Python :: 2.7
Classifier: Programming Language :: Python :: 3.7
Requires-Dist: paramiko
Requires-Dist: pytest
